anc/.DS_Store
anc/__init__.py
anc/api/__init__.py
anc/api/connection.py
anc/cli/__init__.py
anc/cli/cli.py
anc/cli/dataset.py
anc/cli/deployment.py
anc/cli/evaluation.py
anc/cli/load_test/__init__.py
anc/cli/load_test/backend_request_func.py
anc/cli/load_test/data_analysis.py
anc/cli/load_test/input_data_analysis.py
anc/cli/load_test/load_testing_operator.py
anc/cli/load_test/metric_collector.py
anc/cli/load_test/multidialog_processor.py
anc/cli/load_test/prometheus_metric.py
anc/cli/load_test/server.py
anc/cli/load_test/test.py
anc/cli/load_test/util.py
anc/cli/load_testing.py
anc/cli/operators/airflow_operator.py
anc/cli/operators/dataset_operator.py
anc/cli/operators/eval_operator.py
anc/cli/quantization.py
anc/cli/util.py
anc/conf/__init__.py
anc/conf/remote.py
anc/data/__init__.py
anc/data/anc_composer.py
anc/data/anc_dataloader.py
anc/data/anc_dataset.py
anc/data/anc_processor.py
anc/data/anc_sampler.py
anc/data/eval/__init__.py
anc/data/eval/token_cache.py
anc/data/eval/token_cache_sft.py
anc/data/jsonl_dataset.py
anc/data/load.py
anc/data/parquet_dataset.py
anc/data/processors/llm_processor.py
anc/data/processors/tokenizer.py
anc/data/sequential_indexed_dataset.py
anc/data/test/test_loader_ckpt.py
anc/data/test/test_sampler.py
anc/data/utils.py
anc/eval/__init__.py
anc/eval/llm/__init__.py
anc/eval/llm/callbacks/__init__.py
anc/eval/llm/callbacks/lightning/__init__.py
anc/eval/llm/callbacks/lightning/auto.py
anc/eval/llm/triggers/__init__.py
anc/eval/llm/triggers/workflow.py
anc/eval/llm_v2/__init__.py
anc/eval/llm_v2/callbacks/__init__.py
anc/eval/llm_v2/callbacks/megatron/__init__.py
anc/eval/llm_v2/callbacks/megatron/auto.py
anc/eval/llm_v2/triggers/__init__.py
anc/eval/llm_v2/triggers/workflow.py
anc/eval/rank_zero.py
anc/eval/utils.py
anc/eval/voice/__init__.py
anc/eval/voice/triggers/__init__.py
anc/eval/voice/triggers/workflow.py
anc/scripts/get_step_info.py
anc/test/test_cli.py
anc/version.py
pyproject.toml
anc-0.4.26.dist-info/METADATA
anc-0.4.26.dist-info/WHEEL
anc-0.4.26.dist-info/entry_points.txt
anc-0.4.26.dist-info/RECORD
